MANIFEST.in
README
README.rst
setup.cfg
setup.py
django_redirect_middleware.egg-info/PKG-INFO
django_redirect_middleware.egg-info/SOURCES.txt
django_redirect_middleware.egg-info/dependency_links.txt
django_redirect_middleware.egg-info/requires.txt
django_redirect_middleware.egg-info/top_level.txt
redirects/__init__.py
redirects/middleware.py