Metadata-Version: 1.0
Name: django-redirect-middleware
Version: 0.0.1
Summary: Remake of standart Django redirect middleware
Home-page: UNKNOWN
Author: Dmitry Sobolev
Author-email: dmitry.sobolev@redsolution.ru
License: BSD
Platform: UNKNOWN
